skydance/__init__.py
skydance/enum.py
skydance/network/__init__.py
skydance/network/buffer.py
skydance/network/discovery.py
skydance/network/session.py
skydance/protocol.py
skydance/tests/__init__.py
skydance/tests/network/__init__.py
skydance/tests/network/test_buffer.py
skydance/tests/network/test_discovery.py
skydance/tests/network/test_session.py
skydance/tests/test_protocol.py
skydance-1.0.1.dist-info/LICENSE.md
skydance-1.0.1.dist-info/METADATA
skydance-1.0.1.dist-info/WHEEL
skydance-1.0.1.dist-info/RECORD
