Metadata-Version: 2.1
Name: skydance
Version: 1.0.1
Summary: A library for communication with Skydance Wi-Fi relays.
Home-page: https://pypi.org/project/skydance
License: MIT
Author: Tomas Bedrich
Author-email: ja@tbedrich.cz
Requires-Python: >=3.8,<4.0
Classifier: Development Status :: 1 - Planning
Classifier: License :: OSI Approved :: MIT License
Classifier: Natural Language :: English
Classifier: Operating System :: OS Independent
Classifier: Programming Language :: Python
Classifier: Programming Language :: Python :: 3
Classifier: Programming Language :: Python :: 3.8
Classifier: Programming Language :: Python :: 3.9
Classifier: Programming Language :: Python :: 3.10
Classifier: Programming Language :: Python :: 3.11
Classifier: Programming Language :: Python :: 3.12
Classifier: Topic :: Home Automation
Classifier: Topic :: System :: Hardware
Classifier: Topic :: System :: Networking
Project-URL: Documentation, https://skydance.readthedocs.io
Project-URL: Repository, https://github.com/tomasbedrich/skydance
